ddlcheck/__init__.py
ddlcheck/checks/__init__.py
ddlcheck/checks/add_column.py
ddlcheck/checks/alter_column_type.py
ddlcheck/checks/create_index.py
ddlcheck/checks/drop_column.py
ddlcheck/checks/drop_table.py
ddlcheck/checks/rename_column.py
ddlcheck/checks/set_not_null.py
ddlcheck/checks/truncate.py
ddlcheck/checks/update_without_filter.py
ddlcheck/cli.py
ddlcheck/core/__init__.py
ddlcheck/core/check.py
ddlcheck/core/utils.py
ddlcheck/logger.py
ddlcheck/models.py
ddlcheck-0.1.0.dist-info/METADATA
ddlcheck-0.1.0.dist-info/WHEEL
ddlcheck-0.1.0.dist-info/entry_points.txt
ddlcheck-0.1.0.dist-info/RECORD
