Metadata-Version: 2.3
Name: ddlcheck
Version: 0.1.0
Summary: CLI tool to analyze SQL migrations for potential production database risks
Author: Oliver Rice
Author-email: github@oliverrice.com
Requires-Python: >=3.12
Classifier: Programming Language :: Python :: 3
Classifier: Programming Language :: Python :: 3.12
Classifier: Programming Language :: Python :: 3.13
Requires-Dist: mkdocs (>=1.6.1,<2.0.0)
Requires-Dist: mkdocs-material (>=9.6.12,<10.0.0)
Requires-Dist: pglast (>=7.7,<8.0)
Requires-Dist: pre-commit (>=4.2.0,<5.0.0)
Requires-Dist: pymdown-extensions (>=10.14.3,<11.0.0)
Requires-Dist: pytest (>=8.3.5,<9.0.0)
Requires-Dist: pytest-cov (>=6.1.1,<7.0.0)
Requires-Dist: rich (>=14.0.0,<15.0.0)
Requires-Dist: toml (>=0.10.2,<0.11.0)
Requires-Dist: typer (>=0.15.2,<0.16.0)
